pycoare/__init__.py
pycoare/coare_35.py
pycoare/coare_36.py
pycoare/util.py
pycoare-0.3.0.dist-info/licenses/LICENSE
pycoare-0.3.0.dist-info/METADATA
pycoare-0.3.0.dist-info/WHEEL
pycoare-0.3.0.dist-info/top_level.txt
pycoare-0.3.0.dist-info/RECORD
