Metadata-Version: 2.4
Name: pycoare
Version: 0.3.0
Summary: A Python implementation of the COARE bulk air-sea flux algorithm.
Author-email: Andrew Scherer <scherand@oregonstate.edu>
Maintainer-email: Andrew Scherer <scherand@oregonstate.edu>
License: MIT License
Project-URL: Source, https://github.com/pyCOARE/coare
Keywords: oceanography,air-sea,bulk flux
Classifier: Development Status :: 4 - Beta
Classifier: Programming Language :: Python
Classifier: License :: OSI Approved :: MIT License
Classifier: Operating System :: OS Independent
Classifier: Topic :: Scientific/Engineering
Classifier: Intended Audience :: Science/Research
Requires-Python: >=3.9
License-File: LICENSE
Requires-Dist: numpy
Dynamic: license-file
